{
  "users": [
    {
      "name": "Bright Patani",
      "age": 20,
      "occupation": "Python Programmer",
      "id": "781b"
    },
    {
      "id": "fbe0",
      "title": "Name: Justin Okpara",
      "body": "Age: 20, Occupation:student",
      "userId": 1
    },
    {
      "id": "5f96",
      "title": "Name: Justin Okpara",
      "body": "Age: 20, Occupation:student",
      "userId": 1
    },
    {
      "id": "e65b",
      "name": "Okpara Justin ",
      "age": {},
      "occupation": "student"
    },
    {
      "id": "75bb",
      "name": "Okpara Justin ",
      "age": {},
      "occupation": "student"
    },
    {
      "id": "fed6",
      "name": "Justin Okpara",
      "age": {},
      "occupation": "student"
    },
    {
      "id": "d9ea",
      "name": "Okpara Justin ",
      "age": {},
      "occupation": "student"
    },
    {
      "id": "11cf",
      "name": "Paul Ebinike",
      "age": {},
      "occupation": "trader"
    },
    {
      "id": "8573",
      "name": "Nwankwo Stephen chiaghanam",
      "age": {},
      "occupation": "i dont know"
    },
    {
      "id": "042b",
      "name": "Command Day Secondary Sch",
      "age": {},
      "occupation": "ffffffff"
    },
    {
      "id": "8c52",
      "name": "",
      "age": {},
      "occupation": ""
    },
    {
      "id": "1d01",
      "name": "Justin Okpara",
      "age": {},
      "occupation": ""
    },
    {
      "id": "b70c",
      "name": "",
      "age": {},
      "occupation": ""
    },
    {
      "id": "dde3",
      "name": "",
      "age": {},
      "occupation": ""
    },
    {
      "id": "2b67",
      "name": "",
      "age": {},
      "occupation": ""
    },
    {
      "id": "beaa",
      "name": "",
      "age": {},
      "occupation": ""
    },
    {
      "id": "5523",
      "name": "",
      "age": {},
      "occupation": ""
    },
    {
      "id": "4652",
      "name": "",
      "age": {},
      "occupation": ""
    },
    {
      "id": "6757",
      "name": "",
      "age": {},
      "occupation": ""
    },
    {
      "id": "f466",
      "name": "",
      "age": {},
      "occupation": ""
    },
    {
      "id": "64b3",
      "name": "",
      "age": {},
      "occupation": ""
    },
    {
      "id": "e121",
      "name": "",
      "age": {},
      "occupation": ""
    },
    {
      "id": "0381",
      "name": "",
      "age": {},
      "occupation": ""
    },
    {
      "id": "2532",
      "name": "",
      "age": {},
      "occupation": ""
    },
    {
      "id": "c9de",
      "name": "",
      "age": {},
      "occupation": ""
    },
    {
      "id": "ab1d",
      "name": "",
      "age": {},
      "occupation": ""
    },
    {
      "id": "6d7c",
      "name": "",
      "age": {},
      "occupation": ""
    },
    {
      "id": "3039",
      "name": "",
      "age": {},
      "occupation": ""
    },
    {
      "id": "e65f",
      "name": "",
      "age": {},
      "occupation": ""
    },
    {
      "id": "4825",
      "name": "",
      "age": {},
      "occupation": ""
    },
    {
      "id": "7ad4",
      "name": "",
      "age": {},
      "occupation": ""
    },
    {
      "id": "2031",
      "name": "",
      "age": {},
      "occupation": ""
    },
    {
      "id": "6a20",
      "name": "Justin",
      "age": "",
      "occupation": ""
    },
    {
      "id": "4b12",
      "name": "carti",
      "age": "",
      "occupation": ""
    },
    {
      "id": "a2fd",
      "name": "Justin",
      "age": "9999989",
      "occupation": "hcvvdhyfvbvfyfvhyvf"
    },
    {
      "id": "ff72",
      "name": "Nwankwo Stephen chiaghanam",
      "age": "oooooooooooooooooo",
      "occupation": "888888888888888"
    },
    {
      "id": "f80d",
      "name": "",
      "age": "",
      "occupation": ""
    },
    {
      "id": "f971",
      "name": "",
      "age": "",
      "occupation": ""
    },
    {
      "id": "1db9",
      "name": "",
      "age": "",
      "occupation": ""
    }
  ]
}